LICENSE
README.md
setup.py
sdownloader/__init__.py
sdownloader/fetch.py
sdownloader/main.py
sdownloader/utils.py
sdownloader.egg-info/PKG-INFO
sdownloader.egg-info/SOURCES.txt
sdownloader.egg-info/dependency_links.txt
sdownloader.egg-info/entry_points.txt
sdownloader.egg-info/requires.txt
sdownloader.egg-info/top_level.txt