Metadata-Version: 2.1
Name: sdownloader
Version: 0.1.4
Summary: A little program to download given list of matrices from SuiteSparse.
Home-page: https://github.com/talhaokur/sdownloader
Author: Talha Okur
Author-email: talhao@acm.org
License: MIT
Project-URL: Source, https://github.com/talhaokur/sdownloader
Project-URL: Tracker, https://github.com/talhaokur/sdownloader/issues
Platform: UNKNOWN
Classifier: Programming Language :: Python :: 3
Classifier: Development Status :: 4 - Beta
Classifier: Environment :: Console
Classifier: License :: OSI Approved :: MIT License
Classifier: Operating System :: POSIX :: Linux
Classifier: Intended Audience :: Science/Research
Requires-Python: >=3
License-File: LICENSE
